{
	"name": "FlattenJson",
	"properties": {
		"type": "MappingDataFlow",
		"typeProperties": {
			"sources": [
				{
					"dataset": {
						"referenceName": "SampleDB_container",
						"type": "DatasetReference"
					},
					"name": "RawMovies"
				}
			],
			"sinks": [
				{
					"dataset": {
						"referenceName": "datalake_silver",
						"type": "DatasetReference"
					},
					"name": "SilverMovies"
				}
			],
			"transformations": [
				{
					"name": "FlattenActors"
				}
			],
			"script": "parameters{\n\tcontainer as string ('movies')\n}\nsource(output(\n\t\tactors as (name as string)[],\n\t\tavailabilityDate as timestamp,\n\t\tgenre as string,\n\t\trating as string,\n\t\treleaseYear as short,\n\t\truntime as short,\n\t\tstreamingAvailabilityDate as timestamp,\n\t\ttier as short,\n\t\ttitle as string\n\t),\n\tallowSchemaDrift: true,\n\tvalidateSchema: false,\n\tformat: 'document',\n\tsystemColumns: true) ~> RawMovies\nRawMovies foldDown(unroll(actors),\n\tmapColumn(\n\t\tactorName = actors,\n\t\tavailabilityDate,\n\t\tgenre,\n\t\trating,\n\t\treleaseYear,\n\t\truntime,\n\t\tstreamingAvailabilityDate,\n\t\ttier,\n\t\ttitle,\n\t\tid\n\t),\n\tskipDuplicateMapInputs: false,\n\tskipDuplicateMapOutputs: false) ~> FlattenActors\nFlattenActors sink(allowSchemaDrift: true,\n\tvalidateSchema: false,\n\tformat: 'parquet',\n\tfilePattern:'',\n\ttruncate: true,\n\tumask: 0022,\n\tskipDuplicateMapInputs: true,\n\tskipDuplicateMapOutputs: true) ~> SilverMovies"
		}
	}
}