{
	"name": "FlattenJson",
	"properties": {
		"type": "MappingDataFlow",
		"typeProperties": {
			"sources": [
				{
					"dataset": {
						"referenceName": "SampleDB_movies",
						"type": "DatasetReference"
					},
					"name": "Movies"
				}
			],
			"sinks": [],
			"transformations": [],
			"script": "parameters{\n\tcontainer as string ('movies')\n}\nsource(output(\n\t\tactors as (name as string)[],\n\t\tavailabilityDate as string,\n\t\tgenre as string,\n\t\trating as string,\n\t\treleaseYear as string,\n\t\truntime as string,\n\t\tstreamingAvailabilityDate as string,\n\t\ttier as string,\n\t\ttitle as string\n\t),\n\tallowSchemaDrift: true,\n\tvalidateSchema: false,\n\tformat: 'document',\n\tsystemColumns: true) ~> Movies"
		}
	}
}