{
	"name": "src_datalake_json",
	"properties": {
		"linkedServiceName": {
			"referenceName": "ba-synapseanalytics01-WorkspaceDefaultStorage",
			"type": "LinkedServiceReference"
		},
		"parameters": {
			"srcFileSystem": {
				"type": "string"
			},
			"srcFolder": {
				"type": "string"
			},
			"srcFile": {
				"type": "string"
			}
		},
		"folder": {
			"name": "azure"
		},
		"annotations": [],
		"type": "Json",
		"typeProperties": {
			"location": {
				"type": "AzureBlobFSLocation",
				"fileName": {
					"value": "@dataset().srcFile",
					"type": "Expression"
				},
				"folderPath": {
					"value": "@dataset().srcFolder",
					"type": "Expression"
				},
				"fileSystem": {
					"value": "@dataset().srcFileSystem",
					"type": "Expression"
				}
			}
		},
		"schema": {
			"type": "object",
			"properties": {
				"actors": {
					"type": "array",
					"items": {
						"type": "object",
						"properties": {
							"name": {
								"type": "string"
							}
						}
					}
				},
				"availabilityDate": {
					"type": "string"
				},
				"genre": {
					"type": "string"
				},
				"rating": {
					"type": "string"
				},
				"releaseYear": {
					"type": "integer"
				},
				"runtime": {
					"type": "integer"
				},
				"streamingAvailabilityDate": {
					"type": "string"
				},
				"tier": {
					"type": "integer"
				},
				"title": {
					"type": "string"
				},
				"id": {
					"type": "string"
				},
				"_rid": {
					"type": "string"
				},
				"_self": {
					"type": "string"
				},
				"_etag": {
					"type": "string"
				},
				"_attachments": {
					"type": "string"
				},
				"_ts": {
					"type": "integer"
				}
			}
		}
	}
}